Metadata-Version: 2.2
Name: smartjoiner
Version: 1.0.0
Summary: A smart and flexible string joining library for Python developers.
Author: Khalid Sulaiman Al-Mulaify
Author-email: khalidmfy@gmail.com
Classifier: Programming Language :: Python :: 3
Classifier: License :: OSI Approved :: MIT License
Classifier: Operating System :: OS Independent
Classifier: Intended Audience :: Developers
Classifier: Topic :: Software Development :: Libraries :: Python Modules
Requires-Python: >=3.6
License-File: LICENSE.txt
Dynamic: author
Dynamic: author-email
Dynamic: classifier
Dynamic: description
Dynamic: description-content-type
Dynamic: requires-python
Dynamic: summary
